{
  "resourceType": "CodeSystem",
  "url": "http://purl.org/ga4gh/kin.fhir",
  "version": "20210805",
  "name": "FamilyHistoryRelationsOntology",
  "title": "Family History Relations Ontology",
  "status": "draft",
  "experimental": false,
  "description": "A family relationships ontology.",
  "valueSet": "http://purl.org/ga4gh/kin.fhir?vs",
  "hierarchyMeaning": "is-a",
  "compositional": false,
  "versionNeeded": false,
  "content": "complete",
  "count": 49,
  "filter": [ {
    "code": "root",
    "operator": [ "=" ],
    "value": "True or false."
  }, {
    "code": "deprecated",
    "operator": [ "=" ],
    "value": "True or false."
  }, {
    "code": "imported",
    "operator": [ "=" ],
    "value": "True or false"
  } ],
  "property": [ {
    "code": "parent",
    "description": "Parent codes.",
    "type": "code"
  }, {
    "code": "imported",
    "description": "Indicates if the concept is imported from another code system.",
    "type": "boolean"
  }, {
    "code": "root",
    "description": "Indicates if this concept is a root concept (i.e. Thing is equivalent or a direct parent)",
    "type": "boolean"
  }, {
    "code": "deprecated",
    "description": "Indicates if this concept is deprecated.",
    "type": "boolean"
  } ],
  "concept": [ {
    "code": "KIN:994",
    "display": "Man",
    "property": [ {
      "code": "imported",
      "valueBoolean": false
    }, {
      "code": "parent",
      "valueCode": "KIN:998"
    }, {
      "code": "root",
      "valueBoolean": false
    }, {
      "code": "deprecated",
      "valueBoolean": false
    } ]
  }, {
    "code": "KIN:993",
    "display": "Woman",
    "property": [ {
      "code": "imported",
      "valueBoolean": false
    }, {
      "code": "parent",
      "valueCode": "KIN:998"
    }, {
      "code": "root",
      "valueBoolean": false
    }, {
      "code": "deprecated",
      "valueBoolean": false
    } ]
  }, {
    "code": "KIN:996",
    "display": "Male",
    "property": [ {
      "code": "imported",
      "valueBoolean": false
    }, {
      "code": "parent",
      "valueCode": "KIN:997"
    }, {
      "code": "root",
      "valueBoolean": false
    }, {
      "code": "deprecated",
      "valueBoolean": false
    } ]
  }, {
    "code": "KIN:995",
    "display": "Female",
    "property": [ {
      "code": "imported",
      "valueBoolean": false
    }, {
      "code": "parent",
      "valueCode": "KIN:997"
    }, {
      "code": "root",
      "valueBoolean": false
    }, {
      "code": "deprecated",
      "valueBoolean": false
    } ]
  }, {
    "code": "KIN:998",
    "display": "Person",
    "property": [ {
      "code": "imported",
      "valueBoolean": false
    }, {
      "code": "parent",
      "valueCode": "Thing"
    }, {
      "code": "root",
      "valueBoolean": false
    }, {
      "code": "deprecated",
      "valueBoolean": false
    } ]
  }, {
    "code": "KIN:997",
    "display": "Sex",
    "property": [ {
      "code": "imported",
      "valueBoolean": false
    }, {
      "code": "parent",
      "valueCode": "Thing"
    }, {
      "code": "root",
      "valueBoolean": false
    }, {
      "code": "deprecated",
      "valueBoolean": false
    } ]
  }, {
    "code": "KIN:992",
    "display": "UnknownSex",
    "property": [ {
      "code": "imported",
      "valueBoolean": false
    }, {
      "code": "parent",
      "valueCode": "KIN:997"
    }, {
      "code": "root",
      "valueBoolean": false
    }, {
      "code": "deprecated",
      "valueBoolean": false
    } ]
  }, {
    "code": "KIN:991",
    "display": "OtherSex",
    "property": [ {
      "code": "imported",
      "valueBoolean": false
    }, {
      "code": "parent",
      "valueCode": "KIN:997"
    }, {
      "code": "root",
      "valueBoolean": false
    }, {
      "code": "deprecated",
      "valueBoolean": false
    } ]
  }, {
    "code": "Thing",
    "display": "Thing",
    "property": [ {
      "code": "imported",
      "valueBoolean": false
    }, {
      "code": "root",
      "valueBoolean": true
    }, {
      "code": "deprecated",
      "valueBoolean": false
    } ]
  }, {
    "code": "KIN:001",
    "display": "isRelativeOf",
    "property": [ {
      "code": "imported",
      "valueBoolean": false
    }, {
      "code": "parent",
      "valueCode": "topObjectProperty"
    }, {
      "code": "root",
      "valueBoolean": false
    }, {
      "code": "deprecated",
      "valueBoolean": false
    } ]
  }, {
    "code": "KIN:002",
    "display": "isBiologicalRelativeOf",
    "property": [ {
      "code": "imported",
      "valueBoolean": false
    }, {
      "code": "parent",
      "valueCode": "KIN:001"
    }, {
      "code": "root",
      "valueBoolean": false
    }, {
      "code": "deprecated",
      "valueBoolean": false
    } ]
  }, {
    "code": "KIN:003",
    "display": "isBiologicalParentOf",
    "property": [ {
      "code": "imported",
      "valueBoolean": false
    }, {
      "code": "parent",
      "valueCode": "KIN:002"
    }, {
      "code": "root",
      "valueBoolean": false
    }, {
      "code": "deprecated",
      "valueBoolean": false
    } ]
  }, {
    "code": "KIN:004",
    "display": "isSpermDonorOf",
    "property": [ {
      "code": "imported",
      "valueBoolean": false
    }, {
      "code": "parent",
      "valueCode": "KIN:003"
    }, {
      "code": "root",
      "valueBoolean": false
    }, {
      "code": "deprecated",
      "valueBoolean": false
    } ]
  }, {
    "code": "KIN:005",
    "display": "isGestationalCarrierOf",
    "property": [ {
      "code": "imported",
      "valueBoolean": false
    }, {
      "code": "parent",
      "valueCode": "KIN:001"
    }, {
      "code": "root",
      "valueBoolean": false
    }, {
      "code": "deprecated",
      "valueBoolean": false
    } ]
  }, {
    "code": "KIN:006",
    "display": "isSurrogateOvumDonorOf",
    "property": [ {
      "code": "imported",
      "valueBoolean": false
    }, {
      "code": "parent",
      "valueCode": "KIN:038"
    }, {
      "code": "parent",
      "valueCode": "KIN:005"
    }, {
      "code": "root",
      "valueBoolean": false
    }, {
      "code": "deprecated",
      "valueBoolean": false
    } ]
  }, {
    "code": "KIN:007",
    "display": "isBiologicalSiblingOf",
    "property": [ {
      "code": "imported",
      "valueBoolean": false
    }, {
      "code": "parent",
      "valueCode": "KIN:002"
    }, {
      "code": "root",
      "valueBoolean": false
    }, {
      "code": "deprecated",
      "valueBoolean": false
    } ]
  }, {
    "code": "KIN:008",
    "display": "isFullsiblingOf",
    "property": [ {
      "code": "imported",
      "valueBoolean": false
    }, {
      "code": "parent",
      "valueCode": "KIN:007"
    }, {
      "code": "root",
      "valueBoolean": false
    }, {
      "code": "deprecated",
      "valueBoolean": false
    } ]
  }, {
    "code": "KIN:009",
    "display": "isTwinOf",
    "property": [ {
      "code": "imported",
      "valueBoolean": false
    }, {
      "code": "parent",
      "valueCode": "KIN:008"
    }, {
      "code": "root",
      "valueBoolean": false
    }, {
      "code": "deprecated",
      "valueBoolean": false
    } ]
  }, {
    "code": "KIN:010",
    "display": "isMonozygoticTwinOf",
    "property": [ {
      "code": "imported",
      "valueBoolean": false
    }, {
      "code": "parent",
      "valueCode": "KIN:009"
    }, {
      "code": "root",
      "valueBoolean": false
    }, {
      "code": "deprecated",
      "valueBoolean": false
    } ]
  }, {
    "code": "KIN:011",
    "display": "isPolyzygoticTwinOf",
    "property": [ {
      "code": "imported",
      "valueBoolean": false
    }, {
      "code": "parent",
      "valueCode": "KIN:009"
    }, {
      "code": "root",
      "valueBoolean": false
    }, {
      "code": "deprecated",
      "valueBoolean": false
    } ]
  }, {
    "code": "KIN:012",
    "display": "isHalfSiblingOf",
    "property": [ {
      "code": "imported",
      "valueBoolean": false
    }, {
      "code": "parent",
      "valueCode": "KIN:007"
    }, {
      "code": "root",
      "valueBoolean": false
    }, {
      "code": "deprecated",
      "valueBoolean": false
    } ]
  }, {
    "code": "KIN:013",
    "display": "isParentalSiblingOf",
    "property": [ {
      "code": "imported",
      "valueBoolean": false
    }, {
      "code": "parent",
      "valueCode": "KIN:002"
    }, {
      "code": "root",
      "valueBoolean": false
    }, {
      "code": "deprecated",
      "valueBoolean": false
    } ]
  }, {
    "code": "KIN:014",
    "display": "isCousinOf",
    "property": [ {
      "code": "imported",
      "valueBoolean": false
    }, {
      "code": "parent",
      "valueCode": "KIN:002"
    }, {
      "code": "root",
      "valueBoolean": false
    }, {
      "code": "deprecated",
      "valueBoolean": false
    } ]
  }, {
    "code": "KIN:015",
    "display": "isMaternalCousinOf",
    "property": [ {
      "code": "imported",
      "valueBoolean": false
    }, {
      "code": "parent",
      "valueCode": "KIN:014"
    }, {
      "code": "root",
      "valueBoolean": false
    }, {
      "code": "deprecated",
      "valueBoolean": false
    } ]
  }, {
    "code": "KIN:016",
    "display": "isPaternalCousinOf",
    "property": [ {
      "code": "imported",
      "valueBoolean": false
    }, {
      "code": "parent",
      "valueCode": "KIN:014"
    }, {
      "code": "root",
      "valueBoolean": false
    }, {
      "code": "deprecated",
      "valueBoolean": false
    } ]
  }, {
    "code": "KIN:017",
    "display": "isGrandparentOf",
    "property": [ {
      "code": "imported",
      "valueBoolean": false
    }, {
      "code": "parent",
      "valueCode": "KIN:002"
    }, {
      "code": "root",
      "valueBoolean": false
    }, {
      "code": "deprecated",
      "valueBoolean": false
    } ]
  }, {
    "code": "KIN:018",
    "display": "isGreatGrandparentOf",
    "property": [ {
      "code": "imported",
      "valueBoolean": false
    }, {
      "code": "parent",
      "valueCode": "KIN:002"
    }, {
      "code": "root",
      "valueBoolean": false
    }, {
      "code": "deprecated",
      "valueBoolean": false
    } ]
  }, {
    "code": "KIN:019",
    "display": "isSocialLegalRelativeOf",
    "property": [ {
      "code": "imported",
      "valueBoolean": false
    }, {
      "code": "parent",
      "valueCode": "KIN:001"
    }, {
      "code": "root",
      "valueBoolean": false
    }, {
      "code": "deprecated",
      "valueBoolean": false
    } ]
  }, {
    "code": "KIN:020",
    "display": "isParentFigureOf",
    "property": [ {
      "code": "imported",
      "valueBoolean": false
    }, {
      "code": "parent",
      "valueCode": "KIN:019"
    }, {
      "code": "root",
      "valueBoolean": false
    }, {
      "code": "deprecated",
      "valueBoolean": false
    } ]
  }, {
    "code": "KIN:021",
    "display": "isFosterParentOf",
    "property": [ {
      "code": "imported",
      "valueBoolean": false
    }, {
      "code": "parent",
      "valueCode": "KIN:020"
    }, {
      "code": "root",
      "valueBoolean": false
    }, {
      "code": "deprecated",
      "valueBoolean": false
    } ]
  }, {
    "code": "KIN:022",
    "display": "isAdoptiveParentOf",
    "property": [ {
      "code": "imported",
      "valueBoolean": false
    }, {
      "code": "parent",
      "valueCode": "KIN:020"
    }, {
      "code": "root",
      "valueBoolean": false
    }, {
      "code": "deprecated",
      "valueBoolean": false
    } ]
  }, {
    "code": "KIN:023",
    "display": "isStepParentOf",
    "property": [ {
      "code": "imported",
      "valueBoolean": false
    }, {
      "code": "parent",
      "valueCode": "KIN:020"
    }, {
      "code": "root",
      "valueBoolean": false
    }, {
      "code": "deprecated",
      "valueBoolean": false
    } ]
  }, {
    "code": "KIN:024",
    "display": "isSiblingFigureOf",
    "property": [ {
      "code": "imported",
      "valueBoolean": false
    }, {
      "code": "parent",
      "valueCode": "KIN:019"
    }, {
      "code": "root",
      "valueBoolean": false
    }, {
      "code": "deprecated",
      "valueBoolean": false
    } ]
  }, {
    "code": "KIN:025",
    "display": "isStepSiblingOf",
    "property": [ {
      "code": "imported",
      "valueBoolean": false
    }, {
      "code": "parent",
      "valueCode": "KIN:024"
    }, {
      "code": "root",
      "valueBoolean": false
    }, {
      "code": "deprecated",
      "valueBoolean": false
    } ]
  }, {
    "code": "KIN:026",
    "display": "isPartnerOf",
    "property": [ {
      "code": "imported",
      "valueBoolean": false
    }, {
      "code": "parent",
      "valueCode": "KIN:019"
    }, {
      "code": "root",
      "valueBoolean": false
    }, {
      "code": "deprecated",
      "valueBoolean": false
    } ]
  }, {
    "code": "KIN:027",
    "display": "isBiologicalMotherOf",
    "property": [ {
      "code": "imported",
      "valueBoolean": false
    }, {
      "code": "parent",
      "valueCode": "KIN:003"
    }, {
      "code": "root",
      "valueBoolean": false
    }, {
      "code": "deprecated",
      "valueBoolean": false
    } ]
  }, {
    "code": "KIN:028",
    "display": "isBiologicalFatherOf",
    "property": [ {
      "code": "imported",
      "valueBoolean": false
    }, {
      "code": "parent",
      "valueCode": "KIN:003"
    }, {
      "code": "root",
      "valueBoolean": false
    }, {
      "code": "deprecated",
      "valueBoolean": false
    } ]
  }, {
    "code": "KIN:029",
    "display": "isMitochondrialDonorOf",
    "property": [ {
      "code": "imported",
      "valueBoolean": false
    }, {
      "code": "parent",
      "valueCode": "KIN:001"
    }, {
      "code": "root",
      "valueBoolean": false
    }, {
      "code": "deprecated",
      "valueBoolean": false
    } ]
  }, {
    "code": "KIN:030",
    "display": "isConsanguineousPartnerOf",
    "property": [ {
      "code": "imported",
      "valueBoolean": false
    }, {
      "code": "parent",
      "valueCode": "KIN:002"
    }, {
      "code": "parent",
      "valueCode": "KIN:026"
    }, {
      "code": "root",
      "valueBoolean": false
    }, {
      "code": "deprecated",
      "valueBoolean": false
    } ]
  }, {
    "code": "KIN:031",
    "display": "hasSex",
    "property": [ {
      "code": "imported",
      "valueBoolean": false
    }, {
      "code": "parent",
      "valueCode": "topObjectProperty"
    }, {
      "code": "root",
      "valueBoolean": false
    }, {
      "code": "deprecated",
      "valueBoolean": false
    } ]
  }, {
    "code": "KIN:032",
    "display": "isBiologicalChildOf",
    "property": [ {
      "code": "imported",
      "valueBoolean": false
    }, {
      "code": "parent",
      "valueCode": "KIN:002"
    }, {
      "code": "root",
      "valueBoolean": false
    }, {
      "code": "deprecated",
      "valueBoolean": false
    } ]
  }, {
    "code": "KIN:036",
    "display": "isGrandchildOf",
    "property": [ {
      "code": "imported",
      "valueBoolean": false
    }, {
      "code": "parent",
      "valueCode": "KIN:002"
    }, {
      "code": "root",
      "valueBoolean": false
    }, {
      "code": "deprecated",
      "valueBoolean": false
    } ]
  }, {
    "code": "KIN:038",
    "display": "isOvumDonorOf",
    "property": [ {
      "code": "imported",
      "valueBoolean": false
    }, {
      "code": "parent",
      "valueCode": "KIN:003"
    }, {
      "code": "root",
      "valueBoolean": false
    }, {
      "code": "deprecated",
      "valueBoolean": false
    } ]
  }, {
    "code": "KIN:039",
    "display": "hasGestationalCarrier",
    "property": [ {
      "code": "imported",
      "valueBoolean": false
    }, {
      "code": "parent",
      "valueCode": "KIN:001"
    }, {
      "code": "root",
      "valueBoolean": false
    }, {
      "code": "deprecated",
      "valueBoolean": false
    } ]
  }, {
    "code": "KIN:046",
    "display": "hasParentalSibling",
    "property": [ {
      "code": "imported",
      "valueBoolean": false
    }, {
      "code": "parent",
      "valueCode": "KIN:002"
    }, {
      "code": "root",
      "valueBoolean": false
    }, {
      "code": "deprecated",
      "valueBoolean": false
    } ]
  }, {
    "code": "KIN:047",
    "display": "isGreatGrandchildOf",
    "property": [ {
      "code": "imported",
      "valueBoolean": false
    }, {
      "code": "parent",
      "valueCode": "KIN:002"
    }, {
      "code": "root",
      "valueBoolean": false
    }, {
      "code": "deprecated",
      "valueBoolean": false
    } ]
  }, {
    "code": "KIN:050",
    "display": "isSeparatedPartnerOf",
    "property": [ {
      "code": "imported",
      "valueBoolean": false
    }, {
      "code": "parent",
      "valueCode": "KIN:019"
    }, {
      "code": "root",
      "valueBoolean": false
    }, {
      "code": "deprecated",
      "valueBoolean": false
    } ]
  }, {
    "code": "KIN:051",
    "display": "isSeparatedConsanguineousPartnerOf",
    "property": [ {
      "code": "imported",
      "valueBoolean": false
    }, {
      "code": "parent",
      "valueCode": "KIN:050"
    }, {
      "code": "parent",
      "valueCode": "KIN:002"
    }, {
      "code": "root",
      "valueBoolean": false
    }, {
      "code": "deprecated",
      "valueBoolean": false
    } ]
  }, {
    "code": "topObjectProperty",
    "display": "topObjectProperty",
    "property": [ {
      "code": "imported",
      "valueBoolean": false
    }, {
      "code": "root",
      "valueBoolean": true
    }, {
      "code": "deprecated",
      "valueBoolean": false
    } ]
  } ]
}